README.md
setup.py
ovopy/__init__.py
ovopy/constants.py
ovopy/exceptions.py
ovopy/ovo.py
ovopy.egg-info/PKG-INFO
ovopy.egg-info/SOURCES.txt
ovopy.egg-info/dependency_links.txt
ovopy.egg-info/requires.txt
ovopy.egg-info/top_level.txt